{
    "metadata": {
        "run_id": "de294520",
        "timestamp": "2026-04-27T03:41:58.265380",
        "description": "Grid search mapping ns and r sensitivity to initial conditions."
    },
    "model_parameters": {
        "name": "Higgs Inflation",
        "xi": 15000,
        "lambda": 0.13
    },
    "grid_parameters": {
        "phi0_min": 5.4,
        "phi0_max": 6.0,
        "phi0_steps": 360,
        "yi_min": -0.2,
        "yi_max": -0.2,
        "yi_steps": 1,
        "total_configurations_attempted": 360,
        "successful_simulations": 97
    },
    "numerical_settings": {
        "delta_finite_difference": 1e-05,
        "T_span_bg_max": 1000,
        "T_span_bg_steps": 10000
    },
    "results": [
        {
            "phi0": 5.8745,
            "yi": -0.2,
            "ns": 0.5789620415679599,
            "r": 0.006555650242015075,
            "ns_SR": 3.8278254430004477,
            "r_SR": 12.495541978398755,
            "N_total": 60.01497625001294,
            "Ps": 1.7111773185895294e-09
        },
        {
            "phi0": 5.876,
            "yi": -0.2,
            "ns": 0.5803584045930966,
            "r": 0.00657651227302466,
            "ns_SR": 4.903032349296886,
            "r_SR": 8.09419211390948,
            "N_total": 60.08079337409747,
            "Ps": 1.6911459688158865e-09
        },
        {
            "phi0": 5.8775,
            "yi": -0.2,
            "ns": 0.5864971078274098,
            "r": 0.006593776091175099,
            "ns_SR": 5.4072275500079146,
            "r_SR": 5.995531443582602,
            "N_total": 60.15999637224968,
            "Ps": 1.6718173297777397e-09
        },
        {
            "phi0": 5.8790000000000004,
            "yi": -0.2,
            "ns": 0.612751826935958,
            "r": 0.006626379510964316,
            "ns_SR": 5.922226608615555,
            "r_SR": 3.7858783591516585,
            "N_total": 60.239239593588145,
            "Ps": 1.635467053502987e-09
        },
        {
            "phi0": 5.8805000000000005,
            "yi": -0.2,
            "ns": 0.6728474197904741,
            "r": 0.006637558101141346,
            "ns_SR": 6.227596038890491,
            "r_SR": 2.376275699486639,
            "N_total": 60.31852347158702,
            "Ps": 1.5992259770110647e-09
        },
        {
            "phi0": 5.882000000000001,
            "yi": -0.2,
            "ns": 0.7833312184280455,
            "r": 0.006600478328615794,
            "ns_SR": 6.390462084511869,
            "r_SR": 1.4892088414017932,
            "N_total": 60.397848428376236,
            "Ps": 1.5706785094949537e-09
        },
        {
            "phi0": 5.883500000000001,
            "yi": -0.2,
            "ns": 0.8925881943333874,
            "r": 0.006528445266955835,
            "ns_SR": 6.442831736425932,
            "r_SR": 1.0914286112014653,
            "N_total": 60.46392097380183,
            "Ps": 1.5613535677455844e-09
        },
        {
            "phi0": 5.885000000000001,
            "yi": -0.2,
            "ns": 1.116420901723446,
            "r": 0.006343051808415358,
            "ns_SR": 6.458995331644419,
            "r_SR": 0.6870654558206948,
            "N_total": 60.543366276657096,
            "Ps": 1.5650731006171593e-09
        },
        {
            "phi0": 5.8865,
            "yi": -0.2,
            "ns": 1.407778467860534,
            "r": 0.006036379278911409,
            "ns_SR": 6.416943129220895,
            "r_SR": 0.43517606313529406,
            "N_total": 60.62285334303079,
            "Ps": 1.6015936904500557e-09
        },
        {
            "phi0": 5.888,
            "yi": -0.2,
            "ns": 1.7417583281443294,
            "r": 0.005607526965606518,
            "ns_SR": 6.327369608580497,
            "r_SR": 0.27800059273040184,
            "N_total": 60.702382728102485,
            "Ps": 1.6817010592325777e-09
        },
        {
            "phi0": 5.8895,
            "yi": -0.2,
            "ns": 2.072306108385912,
            "r": 0.005085098740499407,
            "ns_SR": 6.195429764267841,
            "r_SR": 0.17956507326571092,
            "N_total": 60.78195476509453,
            "Ps": 1.815424015027144e-09
        },
        {
            "phi0": 5.891,
            "yi": -0.2,
            "ns": 2.2630902383814737,
            "r": 0.004706721124098263,
            "ns_SR": 6.0852991453753935,
            "r_SR": 0.1351591822264379,
            "N_total": 60.84827217283991,
            "Ps": 1.9397194720277265e-09
        },
        {
            "phi0": 5.8925,
            "yi": -0.2,
            "ns": 2.4667613705972853,
            "r": 0.0041514895579787894,
            "ns_SR": 5.886455074908137,
            "r_SR": 0.08945361000201799,
            "N_total": 60.9279644812114,
            "Ps": 2.176141404688807e-09
        },
        {
            "phi0": 5.894,
            "yi": -0.2,
            "ns": 2.5405850649511232,
            "r": 0.00365051680708649,
            "ns_SR": 5.648135643123217,
            "r_SR": 0.060308076062877435,
            "N_total": 61.00770010342582,
            "Ps": 2.470281173525369e-09
        },
        {
            "phi0": 5.8955,
            "yi": -0.2,
            "ns": 2.469101477372189,
            "r": 0.0032382834092898817,
            "ns_SR": 5.371621768584548,
            "r_SR": 0.041540688136658885,
            "N_total": 61.08747942004488,
            "Ps": 2.804988402094635e-09
        },
        {
            "phi0": 5.897,
            "yi": -0.2,
            "ns": 2.25332960643484,
            "r": 0.002929069722312339,
            "ns_SR": 5.060001832076152,
            "r_SR": 0.029318763625400195,
            "N_total": 61.1673028073384,
            "Ps": 3.147839108535235e-09
        },
        {
            "phi0": 5.8985,
            "yi": -0.2,
            "ns": 2.0345276620610404,
            "r": 0.002778626392627101,
            "ns_SR": 4.835945091316108,
            "r_SR": 0.023581027512111528,
            "N_total": 61.233853657440065,
            "Ps": 3.360821417154484e-09
        },
        {
            "phi0": 5.9,
            "yi": -0.2,
            "ns": 1.6073926815421073,
            "r": 0.0026406564996541712,
            "ns_SR": 4.479411265598345,
            "r_SR": 0.01742686715220884,
            "N_total": 61.31379691208829,
            "Ps": 3.607281449480208e-09
        },
        {
            "phi0": 5.9012658227848105,
            "yi": -0.2,
            "ns": 1.0893305784853689,
            "r": 0.0026008541797642045,
            "ns_SR": 4.107736252115974,
            "r_SR": 0.013272950401722309,
            "N_total": 61.38752782592958,
            "Ps": 3.721764660271924e-09
        },
        {
            "phi0": 5.902531645569621,
            "yi": -0.2,
            "ns": 0.7212951599828661,
            "r": 0.0026251442081989943,
            "ns_SR": 3.8577141002662065,
            "r_SR": 0.011255977885837478,
            "N_total": 61.447979813426215,
            "Ps": 3.7103738961557595e-09
        },
        {
            "phi0": 5.903797468354431,
            "yi": -0.2,
            "ns": 0.37103559929248986,
            "r": 0.002690246808305163,
            "ns_SR": 3.609491298960951,
            "r_SR": 0.009676341773540757,
            "N_total": 61.50843901556428,
            "Ps": 3.626186475648522e-09
        },
        {
            "phi0": 5.905063291139241,
            "yi": -0.2,
            "ns": -0.004191772884140743,
            "r": 0.0028576071050565905,
            "ns_SR": 3.246984575911075,
            "r_SR": 0.007913620973898201,
            "N_total": 61.58229704763166,
            "Ps": 3.3915020512958437e-09
        },
        {
            "phi0": 5.906329113924051,
            "yi": -0.2,
            "ns": -0.04676837645806531,
            "r": 0.0029932710783453194,
            "ns_SR": 3.017184003637029,
            "r_SR": 0.0070302511599716205,
            "N_total": 61.64284176436754,
            "Ps": 3.2095710813924684e-09
        },
        {
            "phi0": 5.907594936708861,
            "yi": -0.2,
            "ns": 0.35401716084412416,
            "r": 0.0031697318062914614,
            "ns_SR": 2.6947785218364784,
            "r_SR": 0.006026339251381324,
            "N_total": 61.71674982714776,
            "Ps": 2.988136573197184e-09
        },
        {
            "phi0": 5.908860759493671,
            "yi": -0.2,
            "ns": 0.881476896851851,
            "r": 0.00321196638926377,
            "ns_SR": 2.4980721900509333,
            "r_SR": 0.005512458779063851,
            "N_total": 61.777379950992234,
            "Ps": 2.9307387733856555e-09
        },
        {
            "phi0": 5.910126582278481,
            "yi": -0.2,
            "ns": 1.4152897565178757,
            "r": 0.00317402483063502,
            "ns_SR": 2.316784361052026,
            "r_SR": 0.005094650229650788,
            "N_total": 61.838015529379305,
            "Ps": 2.9625510337274724e-09
        },
        {
            "phi0": 5.9113924050632916,
            "yi": -0.2,
            "ns": 1.751871392552104,
            "r": 0.003025920161305418,
            "ns_SR": 2.074107980227557,
            "r_SR": 0.004610305177538084,
            "N_total": 61.91205479561438,
            "Ps": 3.131281983557305e-09
        },
        {
            "phi0": 5.912658227848102,
            "yi": -0.2,
            "ns": 1.5374162474761992,
            "r": 0.002932325637059113,
            "ns_SR": 1.9323301029073203,
            "r_SR": 0.004355818462459934,
            "N_total": 61.97277498018075,
            "Ps": 3.255848392539587e-09
        },
        {
            "phi0": 5.913924050632912,
            "yi": -0.2,
            "ns": 0.8140351237837051,
            "r": 0.0028971559168884248,
            "ns_SR": 1.7473386962622972,
            "r_SR": 0.004058201950019546,
            "N_total": 62.046867682661,
            "Ps": 3.3151818422644425e-09
        },
        {
            "phi0": 5.915189873417722,
            "yi": -0.2,
            "ns": 0.410439444277389,
            "r": 0.002949112659495622,
            "ns_SR": 1.6417219738374182,
            "r_SR": 0.0038992242129390372,
            "N_total": 62.107672141836936,
            "Ps": 3.248602205628732e-09
        },
        {
            "phi0": 5.916455696202532,
            "yi": -0.2,
            "ns": 0.5428356234461289,
            "r": 0.0030675058909602664,
            "ns_SR": 1.5065430668893085,
            "r_SR": 0.003712625718471213,
            "N_total": 62.181819741177314,
            "Ps": 3.0956737468355584e-09
        },
        {
            "phi0": 5.917721518987342,
            "yi": -0.2,
            "ns": 1.0848903912454884,
            "r": 0.0030858920161002056,
            "ns_SR": 1.43067233845268,
            "r_SR": 0.003611341116734766,
            "N_total": 62.242708186410674,
            "Ps": 3.0688772636618397e-09
        },
        {
            "phi0": 5.918987341772152,
            "yi": -0.2,
            "ns": 1.4815482183427828,
            "r": 0.003034173010948743,
            "ns_SR": 1.3647107823263849,
            "r_SR": 0.003526405570734012,
            "N_total": 62.30359978645286,
            "Ps": 3.1295741768818765e-09
        },
        {
            "phi0": 5.9202531645569625,
            "yi": -0.2,
            "ns": 1.1054557172199373,
            "r": 0.0029534231361525577,
            "ns_SR": 1.2818152708058967,
            "r_SR": 0.0034271790114703375,
            "N_total": 62.37788422956918,
            "Ps": 3.237265302773424e-09
        },
        {
            "phi0": 5.921518987341773,
            "yi": -0.2,
            "ns": 0.6049932580379007,
            "r": 0.0029714918228066858,
            "ns_SR": 1.2360306272456951,
            "r_SR": 0.003371939800022625,
            "N_total": 62.43885878852423,
            "Ps": 3.215624266839546e-09
        },
        {
            "phi0": 5.922784810126583,
            "yi": -0.2,
            "ns": 0.8071849770396318,
            "r": 0.0030495824674130895,
            "ns_SR": 1.1789744622973892,
            "r_SR": 0.0033081696509375557,
            "N_total": 62.51320137791588,
            "Ps": 3.1145761728934686e-09
        },
        {
            "phi0": 5.924050632911393,
            "yi": -0.2,
            "ns": 1.316368696379719,
            "r": 0.003031105255762103,
            "ns_SR": 1.1476950029443223,
            "r_SR": 0.0032718131040035425,
            "N_total": 62.5742585014104,
            "Ps": 3.135672851565645e-09
        },
        {
            "phi0": 5.925316455696203,
            "yi": -0.2,
            "ns": 0.9596780677200711,
            "r": 0.0029753618323388204,
            "ns_SR": 1.1089366805328218,
            "r_SR": 0.003230736239126838,
            "N_total": 62.64866055654364,
            "Ps": 3.2093756766505667e-09
        },
        {
            "phi0": 5.926582278481013,
            "yi": -0.2,
            "ns": 0.6053308002986921,
            "r": 0.003006459805022375,
            "ns_SR": 1.087798078783516,
            "r_SR": 0.0032065334485065996,
            "N_total": 62.7097999090994,
            "Ps": 3.169336845626097e-09
        },
        {
            "phi0": 5.927848101265823,
            "yi": -0.2,
            "ns": 0.9967101041774418,
            "r": 0.003033875496940924,
            "ns_SR": 1.0697627750220737,
            "r_SR": 0.0031859001872704957,
            "N_total": 62.770939918263295,
            "Ps": 3.1330744225389077e-09
        },
        {
            "phi0": 5.929113924050633,
            "yi": -0.2,
            "ns": 1.091630817240278,
            "r": 0.0029874225503003496,
            "ns_SR": 1.047523120507844,
            "r_SR": 0.003163816664696193,
            "N_total": 62.84548395273804,
            "Ps": 3.1931169258366027e-09
        },
        {
            "phi0": 5.9303797468354436,
            "yi": -0.2,
            "ns": 0.6692563176194717,
            "r": 0.003004343594605432,
            "ns_SR": 1.0354516121983501,
            "r_SR": 0.0031498293587624063,
            "N_total": 62.90670498692972,
            "Ps": 3.171448762963196e-09
        },
        {
            "phi0": 5.931645569620254,
            "yi": -0.2,
            "ns": 1.240073675060715,
            "r": 0.003011970653394129,
            "ns_SR": 1.020594336050623,
            "r_SR": 0.0031358043519427703,
            "N_total": 62.98131152744989,
            "Ps": 3.1611371921856637e-09
        },
        {
            "phi0": 5.932911392405064,
            "yi": -0.2,
            "ns": 0.8585784011312276,
            "r": 0.0029927765391750995,
            "ns_SR": 1.0125491488499239,
            "r_SR": 0.0031261618581207213,
            "N_total": 63.0426131146835,
            "Ps": 3.186255466176931e-09
        },
        {
            "phi0": 5.934177215189874,
            "yi": -0.2,
            "ns": 1.140332435620348,
            "r": 0.0030181962617813513,
            "ns_SR": 1.0026569043933078,
            "r_SR": 0.003117415813884959,
            "N_total": 63.11728346069424,
            "Ps": 3.1533700073782768e-09
        },
        {
            "phi0": 5.935443037974684,
            "yi": -0.2,
            "ns": 0.9323757220927078,
            "r": 0.002995619691443597,
            "ns_SR": 0.9973108778203454,
            "r_SR": 0.0031106218255426755,
            "N_total": 63.17866511178128,
            "Ps": 3.1825101970257266e-09
        },
        {
            "phi0": 5.936708860759494,
            "yi": -0.2,
            "ns": 1.149300031188172,
            "r": 0.0030141636090664664,
            "ns_SR": 0.9907386455559062,
            "r_SR": 0.0031053420400625987,
            "N_total": 63.25340058170411,
            "Ps": 3.158645961648883e-09
        },
        {
            "phi0": 5.937974683544304,
            "yi": -0.2,
            "ns": 0.8292214856563819,
            "r": 0.0030009233072075016,
            "ns_SR": 0.9871936258141409,
            "r_SR": 0.003100418206709941,
            "N_total": 63.31486170498268,
            "Ps": 3.175676876562974e-09
        },
        {
            "phi0": 5.9392405063291145,
            "yi": -0.2,
            "ns": 1.11002709214275,
            "r": 0.0030043235936688993,
            "ns_SR": 0.9828329314893322,
            "r_SR": 0.003097417092396811,
            "N_total": 63.389663578138524,
            "Ps": 3.171472029897729e-09
        },
        {
            "phi0": 5.940506329113925,
            "yi": -0.2,
            "ns": 0.8515644490457858,
            "r": 0.0030127169142120103,
            "ns_SR": 0.9804859081840418,
            "r_SR": 0.00309372133244846,
            "N_total": 63.45120366448853,
            "Ps": 3.160394191306746e-09
        },
        {
            "phi0": 5.941772151898735,
            "yi": -0.2,
            "ns": 1.0292159771915868,
            "r": 0.0030008716168130065,
            "ns_SR": 0.9784961620388225,
            "r_SR": 0.003090389016926539,
            "N_total": 63.52607314956659,
            "Ps": 3.175427509800572e-09
        },
        {
            "phi0": 5.943037974683545,
            "yi": -0.2,
            "ns": 1.099848839058466,
            "r": 0.0030054511764791274,
            "ns_SR": 0.9760428735403975,
            "r_SR": 0.003089328306526642,
            "N_total": 63.58769157935347,
            "Ps": 3.1697859954373375e-09
        },
        {
            "phi0": 5.944303797468355,
            "yi": -0.2,
            "ns": 0.9392916109317426,
            "r": 0.00301117731679344,
            "ns_SR": 0.9747280246964461,
            "r_SR": 0.003086676050328485,
            "N_total": 63.64930567990376,
            "Ps": 3.162098734310947e-09
        },
        {
            "phi0": 5.945569620253165,
            "yi": -0.2,
            "ns": 0.9612683387459653,
            "r": 0.0030119426767321465,
            "ns_SR": 0.973101745399691,
            "r_SR": 0.003086446770103121,
            "N_total": 63.72432606869016,
            "Ps": 3.1614214327405846e-09
        },
        {
            "phi0": 5.946835443037975,
            "yi": -0.2,
            "ns": 0.844476075424747,
            "r": 0.003006053594275141,
            "ns_SR": 0.9722341269173753,
            "r_SR": 0.0030842389081920623,
            "N_total": 63.78601706868041,
            "Ps": 3.1687565534396662e-09
        },
        {
            "phi0": 5.948101265822785,
            "yi": -0.2,
            "ns": 0.8991911896391329,
            "r": 0.0030104555398591175,
            "ns_SR": 0.97115564357408,
            "r_SR": 0.00308455411727518,
            "N_total": 63.86110767203049,
            "Ps": 3.1633618439985713e-09
        },
        {
            "phi0": 5.9493670886075956,
            "yi": -0.2,
            "ns": 0.8590650740553853,
            "r": 0.0030065304851541017,
            "ns_SR": 0.9705841703790458,
            "r_SR": 0.0030826351114077778,
            "N_total": 63.92287490007384,
            "Ps": 3.1681488789934346e-09
        },
        {
            "phi0": 5.950632911392405,
            "yi": -0.2,
            "ns": 1.0195741678855628,
            "r": 0.0030101179726026604,
            "ns_SR": 0.9698683191739059,
            "r_SR": 0.003083305357959673,
            "N_total": 63.998036878116245,
            "Ps": 3.163816593714903e-09
        },
        {
            "phi0": 5.951898734177215,
            "yi": -0.2,
            "ns": 0.9967297849677733,
            "r": 0.00300880302785272,
            "ns_SR": 0.9694928558908816,
            "r_SR": 0.0030815724915423813,
            "N_total": 64.0598796322687,
            "Ps": 3.165219506164262e-09
        },
        {
            "phi0": 5.953164556962025,
            "yi": -0.2,
            "ns": 0.9179459694118215,
            "r": 0.003006717911442751,
            "ns_SR": 0.9690169707291157,
            "r_SR": 0.003082472622955288,
            "N_total": 64.13511411030204,
            "Ps": 3.168222806641072e-09
        },
        {
            "phi0": 5.954430379746835,
            "yi": -0.2,
            "ns": 0.8887457879405213,
            "r": 0.0030063596912684276,
            "ns_SR": 0.9687712058713004,
            "r_SR": 0.0030808580317420323,
            "N_total": 64.19703165473766,
            "Ps": 3.168382463003155e-09
        },
        {
            "phi0": 5.955696202531645,
            "yi": -0.2,
            "ns": 0.9790655484954282,
            "r": 0.00300686861251104,
            "ns_SR": 0.9684540796364436,
            "r_SR": 0.0030819053388727903,
            "N_total": 64.27233974873107,
            "Ps": 3.1680336926138245e-09
        },
        {
            "phi0": 5.9569620253164555,
            "yi": -0.2,
            "ns": 0.8955549463328586,
            "r": 0.0030067823067043784,
            "ns_SR": 0.9682941249845038,
            "r_SR": 0.0030803641728051933,
            "N_total": 64.33433132069024,
            "Ps": 3.1678320027380303e-09
        },
        {
            "phi0": 5.958227848101266,
            "yi": -0.2,
            "ns": 0.9024080912198544,
            "r": 0.0030083215662308326,
            "ns_SR": 0.9680820216506191,
            "r_SR": 0.0030815039787364987,
            "N_total": 64.40971410723145,
            "Ps": 3.166136640152971e-09
        },
        {
            "phi0": 5.959493670886076,
            "yi": -0.2,
            "ns": 1.030450155817488,
            "r": 0.0030069140607821426,
            "ns_SR": 0.967978840529326,
            "r_SR": 0.0030800065919769997,
            "N_total": 64.47177891234315,
            "Ps": 3.1676665448462498e-09
        },
        {
            "phi0": 5.960759493670886,
            "yi": -0.2,
            "ns": 0.9426943430720698,
            "r": 0.003007405712296266,
            "ns_SR": 0.9678362128484894,
            "r_SR": 0.003081202740627467,
            "N_total": 64.54723744603528,
            "Ps": 3.1673167581284693e-09
        },
        {
            "phi0": 5.962025316455696,
            "yi": -0.2,
            "ns": 1.02254462909575,
            "r": 0.0030068058972937124,
            "ns_SR": 0.967770599140588,
            "r_SR": 0.003079729534128661,
            "N_total": 64.60937466121887,
            "Ps": 3.1677914998525806e-09
        },
        {
            "phi0": 5.963291139240506,
            "yi": -0.2,
            "ns": 0.9433219452150327,
            "r": 0.0030085260343677995,
            "ns_SR": 0.9676739368269233,
            "r_SR": 0.003080958109517619,
            "N_total": 64.68490995388454,
            "Ps": 3.1658469567806696e-09
        },
        {
            "phi0": 5.964556962025316,
            "yi": -0.2,
            "ns": 0.9263085040761362,
            "r": 0.00300691454969359,
            "ns_SR": 0.9676331888283038,
            "r_SR": 0.0030794961241166216,
            "N_total": 64.74711872621535,
            "Ps": 3.1676200688589953e-09
        },
        {
            "phi0": 5.965822784810126,
            "yi": -0.2,
            "ns": 0.9480202092198965,
            "r": 0.003008070353334641,
            "ns_SR": 0.967566944318023,
            "r_SR": 0.0030807413015569657,
            "N_total": 64.82273181218589,
            "Ps": 3.1664191976241417e-09
        },
        {
            "phi0": 5.9670886075949365,
            "yi": -0.2,
            "ns": 0.9592638394203657,
            "r": 0.003006692840688226,
            "ns_SR": 0.9675426627737441,
            "r_SR": 0.0030792819674789577,
            "N_total": 64.89834096834737,
            "Ps": 3.1678897575731725e-09
        },
        {
            "phi0": 5.968354430379747,
            "yi": -0.2,
            "ns": 0.9619379327261938,
            "r": 0.003007873090415653,
            "ns_SR": 0.9674965559228037,
            "r_SR": 0.00308053326973524,
            "N_total": 64.96070308428926,
            "Ps": 3.1666442461998105e-09
        },
        {
            "phi0": 5.969620253164557,
            "yi": -0.2,
            "ns": 0.967461191909261,
            "r": 0.0030090858575641927,
            "ns_SR": 0.9674590959063886,
            "r_SR": 0.0030817870150192895,
            "N_total": 65.03639196491662,
            "Ps": 3.1653573598886658e-09
        },
        {
            "phi0": 5.970886075949367,
            "yi": -0.2,
            "ns": 0.967438706251482,
            "r": 0.0030076702168647562,
            "ns_SR": 0.9674504207361926,
            "r_SR": 0.0030803214049696247,
            "N_total": 65.09882380143604,
            "Ps": 3.1668686226280098e-09
        },
        {
            "phi0": 5.972151898734177,
            "yi": -0.2,
            "ns": 0.9674999752857694,
            "r": 0.0030088773350497302,
            "ns_SR": 0.9674233830692205,
            "r_SR": 0.0030815713464953562,
            "N_total": 65.17459334236293,
            "Ps": 3.1655858671749735e-09
        },
        {
            "phi0": 5.973417721518987,
            "yi": -0.2,
            "ns": 0.9675962966366598,
            "r": 0.0030074582749859066,
            "ns_SR": 0.9674203725352789,
            "r_SR": 0.0030800973544826468,
            "N_total": 65.23709393592108,
            "Ps": 3.167099186657742e-09
        },
        {
            "phi0": 5.974683544303797,
            "yi": -0.2,
            "ns": 0.9676621889948928,
            "r": 0.003008661778655829,
            "ns_SR": 0.9674002517456178,
            "r_SR": 0.00308133989023491,
            "N_total": 65.31294503706259,
            "Ps": 3.165818306734612e-09
        },
        {
            "phi0": 5.9759493670886075,
            "yi": -0.2,
            "ns": 0.9677657283941641,
            "r": 0.0030072336368380534,
            "ns_SR": 0.9674010122193816,
            "r_SR": 0.003079855579390363,
            "N_total": 65.3755134177353,
            "Ps": 3.1673407389269275e-09
        },
        {
            "phi0": 5.977215189873418,
            "yi": -0.2,
            "ns": 0.9677467910091715,
            "r": 0.003008427766686998,
            "ns_SR": 0.9673854907869588,
            "r_SR": 0.0030810883138531323,
            "N_total": 65.45144695130962,
            "Ps": 3.1660688637487874e-09
        },
        {
            "phi0": 5.978481012658228,
            "yi": -0.2,
            "ns": 0.9677746068032826,
            "r": 0.0030069880157721756,
            "ns_SR": 0.9673887702607035,
            "r_SR": 0.0030795924022010966,
            "N_total": 65.5140820621248,
            "Ps": 3.1676035653399098e-09
        },
        {
            "phi0": 5.979746835443038,
            "yi": -0.2,
            "ns": 0.9677897463373527,
            "r": 0.0030081702075135937,
            "ns_SR": 0.9673763160355042,
            "r_SR": 0.0030808137364001648,
            "N_total": 65.59009887196699,
            "Ps": 3.1663438497962055e-09
        },
        {
            "phi0": 5.981012658227848,
            "yi": -0.2,
            "ns": 0.9678071626265541,
            "r": 0.0030067177243927328,
            "ns_SR": 0.9673812868541132,
            "r_SR": 0.0030793053751932693,
            "N_total": 65.65279963826401,
            "Ps": 3.1678922366153667e-09
        },
        {
            "phi0": 5.982278481012658,
            "yi": -0.2,
            "ns": 0.9678184886791912,
            "r": 0.003007886823936167,
            "ns_SR": 0.9673708869317602,
            "r_SR": 0.0030805142388686223,
            "N_total": 65.72890058141849,
            "Ps": 3.166646085483389e-09
        },
        {
            "phi0": 5.983544303797468,
            "yi": -0.2,
            "ns": 0.9678201243485688,
            "r": 0.003006421119454519,
            "ns_SR": 0.9673770018798682,
            "r_SR": 0.0030789928653553286,
            "N_total": 65.8050037281984,
            "Ps": 3.1682087958426115e-09
        },
        {
            "phi0": 5.984810126582278,
            "yi": -0.2,
            "ns": 0.9678202081926116,
            "r": 0.0030075765964178627,
            "ns_SR": 0.9673679865934341,
            "r_SR": 0.0030801885364259607,
            "N_total": 65.86785177384921,
            "Ps": 3.1669768417877823e-09
        },
        {
            "phi0": 5.9860759493670885,
            "yi": -0.2,
            "ns": 0.9678195548485661,
            "r": 0.0030087259327921624,
            "ns_SR": 0.9673595686499383,
            "r_SR": 0.003081378290282937,
            "N_total": 65.94404070589457,
            "Ps": 3.165752356108265e-09
        },
        {
            "phi0": 5.987341772151899,
            "yi": -0.2,
            "ns": 0.967826478376983,
            "r": 0.0030072390629409516,
            "ns_SR": 0.9673668110871753,
            "r_SR": 0.0030798357657293805,
            "N_total": 66.00695208700554,
            "Ps": 3.167336711442221e-09
        },
        {
            "phi0": 5.988607594936709,
            "yi": -0.2,
            "ns": 0.9678228705962424,
            "r": 0.0030083744260898434,
            "ns_SR": 0.967359145294419,
            "r_SR": 0.003081011613005152,
            "N_total": 66.08322753372249,
            "Ps": 3.166126809883082e-09
        },
        {
            "phi0": 5.989873417721519,
            "yi": -0.2,
            "ns": 0.9677927492671592,
            "r": 0.0030068739833107065,
            "ns_SR": 0.967366828240982,
            "r_SR": 0.003079455340549155,
            "N_total": 66.14620112858326,
            "Ps": 3.167726000029096e-09
        },
        {
            "phi0": 5.991139240506329,
            "yi": -0.2,
            "ns": 0.9677770238920339,
            "r": 0.0030079952855582895,
            "ns_SR": 0.9673596862847296,
            "r_SR": 0.0030806170085815963,
            "N_total": 66.2225638055506,
            "Ps": 3.1665307754056536e-09
        },
        {
            "phi0": 5.992405063291139,
            "yi": -0.2,
            "ns": 0.9678699335719787,
            "r": 0.0030064812356886406,
            "ns_SR": 0.9673676866549861,
            "r_SR": 0.0030790468598133626,
            "N_total": 66.29893191663199,
            "Ps": 3.168144877261126e-09
        },
        {
            "phi0": 5.993670886075949,
            "yi": -0.2,
            "ns": 0.9678242199168975,
            "r": 0.0030075884098565058,
            "ns_SR": 0.9673609180054944,
            "r_SR": 0.003080194155229745,
            "N_total": 66.3620489851002,
            "Ps": 3.166964391234434e-09
        },
        {
            "phi0": 5.9949367088607595,
            "yi": -0.2,
            "ns": 0.9678418223697253,
            "r": 0.0030086892215148756,
            "ns_SR": 0.9673543124876862,
            "r_SR": 0.0030813349831246887,
            "N_total": 66.43850589585226,
            "Ps": 3.165791551333512e-09
        },
        {
            "phi0": 5.99620253164557,
            "yi": -0.2,
            "ns": 0.9678044964940036,
            "r": 0.003007153738620242,
            "ns_SR": 0.9673626593098186,
            "r_SR": 0.003079742826383429,
            "N_total": 66.50168252927074,
            "Ps": 3.167427752735412e-09
        },
        {
            "phi0": 5.99746835443038,
            "yi": -0.2,
            "ns": 0.9678265352204019,
            "r": 0.003008240340693303,
            "ns_SR": 0.967356284680167,
            "r_SR": 0.0030808690673756463,
            "N_total": 66.578228847148,
            "Ps": 3.1662697084621275e-09
        },
        {
            "phi0": 5.99873417721519,
            "yi": -0.2,
            "ns": 0.9678545021810524,
            "r": 0.0030066912191255356,
            "ns_SR": 0.9673647902388941,
            "r_SR": 0.003079262858925233,
            "N_total": 66.641463799885,
            "Ps": 3.1679209443483276e-09
        },
        {
            "phi0": 6.0,
            "yi": -0.2,
            "ns": 0.967854077810831,
            "r": 0.003007763570963889,
            "ns_SR": 0.9673585953315199,
            "r_SR": 0.003080374421671052,
            "N_total": 66.71810011402088,
            "Ps": 3.1667777251683397e-09
        }
    ]
}